leapseconds/__about__.py
leapseconds/__init__.py
leapseconds/leapseconds.py
leapseconds/py.typed
leapseconds-2023.4.0.dist-info/METADATA
leapseconds-2023.4.0.dist-info/WHEEL
leapseconds-2023.4.0.dist-info/licenses/LICENSE
leapseconds-2023.4.0.dist-info/RECORD
