Metadata-Version: 2.1
Name: leapseconds
Version: 2023.4.0
Summary: Data for official leap seconds, provided as a tuple of Unix timestamps
Project-URL: Homepage, https://github.com/jamielinux/leapseconds
Project-URL: Issues, https://github.com/jamielinux/leapseconds/issues
Project-URL: Source, https://github.com/jamielinux/leapseconds
Author-email: Jamie Nguyen <j@jamielinux.com>
License-Expression: MIT
License-File: LICENSE
Keywords: iers,leap,seconds
Classifier: Development Status :: 5 - Production/Stable
Classifier: Intended Audience :: Developers
Classifier: License :: OSI Approved :: MIT License
Classifier: Programming Language :: Python
Classifier: Programming Language :: Python :: 3.7
Classifier: Programming Language :: Python :: 3.8
Classifier: Programming Language :: Python :: 3.9
Classifier: Programming Language :: Python :: 3.10
Classifier: Programming Language :: Python :: 3.11
Classifier: Programming Language :: Python :: Implementation :: CPython
Classifier: Programming Language :: Python :: Implementation :: PyPy
Classifier: Topic :: Software Development :: Libraries
Requires-Python: >=3.7
